mjwt/__init__.py
mjwt/_modidx.py
mjwt/utils.py
mjwt-0.0.4.dist-info/LICENSE
mjwt-0.0.4.dist-info/METADATA
mjwt-0.0.4.dist-info/WHEEL
mjwt-0.0.4.dist-info/entry_points.txt
mjwt-0.0.4.dist-info/top_level.txt
mjwt-0.0.4.dist-info/RECORD
